report_on_interval/__init__.py
report_on_interval-0.1.0.dist-info/METADATA
report_on_interval-0.1.0.dist-info/RECORD
report_on_interval-0.1.0.dist-info/WHEEL
report_on_interval-0.1.0.dist-info/top_level.txt
tests/__init__.py
tests/test_report_on_interval.py
