Metadata-Version: 2.1
Name: report-on-interval
Version: 0.1.0
Summary: Print out regular status reports while looping over items
Home-page: https://github.com/dusktreader/report-on-interval
Author: Tucker Beck
Author-email: tucker.beck@gmail.com
License: MIT
Platform: UNKNOWN
Classifier: Intended Audience :: Developers
Classifier: Topic :: Software Development :: Libraries :: Python Modules
Classifier: License :: OSI Approved :: MIT License
Classifier: Programming Language :: Python :: 3
Provides-Extra: dev
Provides-Extra: dev
Requires-Dist: flake8; extra == 'dev'
Requires-Dist: pytest; extra == 'dev'
Requires-Dist: sphinx; extra == 'dev'
